giteasychangelog/__init__.py
giteasychangelog/cli.py
giteasychangelog/giteasychangelog.py
giteasychangelog-0.2.0.dist-info/AUTHORS.md
giteasychangelog-0.2.0.dist-info/LICENSE
giteasychangelog-0.2.0.dist-info/METADATA
giteasychangelog-0.2.0.dist-info/WHEEL
giteasychangelog-0.2.0.dist-info/entry_points.txt
giteasychangelog-0.2.0.dist-info/top_level.txt
giteasychangelog-0.2.0.dist-info/RECORD
